VLSI/project/verilog/multiplier.v
`timescale 1ns/10ps
module multiplier (a0,a1,a2,a3,b0,b1,b2,b3,p0,p1,p2,p3,p4,p5,p6,p7);

input a0,a1,a2,a3,b0,b1,b2,b3;
output p0,p1,p2,p3,p4,p5,p6,p7;
wire y0,y1,y2,y3,y4,y5,y6,y7,y8,y9,y10,y11,y12,y13,y14,y15,y16,y17,y18,y19,y20,c0,c1,c2,c3,c4,c5,c6,c7,c8,c9,c10;

//assign Y = ((A | B) & C) & (C & D);
assign p0 = a0 & b0;
assign y0 = a0 & b1;
assign y1 = a1 & b0;
//half adder - 
assign p1 = y0 ^ y1;
assign c0 = y0 & y1;

assign y2 = a1 & b1;
assign y3 = a2 & b0;
assign y4 = a0 & b2;
//half adder - 
assign y5 = y2 ^ y3;
assign c1 = y2 & y3;
//full adder-
assign p2 = (y4 ^ y5) ^ c0;
assign c2 = ((y4 ^ y5) & c0) | (y4 & y5);

assign y6 = a2 & b1;
assign y7 = a3 & b0;
assign y9 = a1 & b2;
//half adder - 
assign y8 = y6 ^ y7;
assign c3 = y6 & y7;
//full adder-
assign y10 = (y9 ^ y8) ^ c1;
assign c4 = ((y9 ^ y8) & c1) | (y9 & y8);
assign y11 = a0 & b3;
//full adder-
assign p3 = (y11 ^ y10) ^ c2;
assign c5 = ((y11 ^ y10) & c2) | (y11 & y10);

assign y12 = a3 & b1;
assign y13 = a2 & b2;
//full adder-
assign y14 = (y12 ^ y13) ^ c3;
assign c6 = ((y12 ^ y13) & c3) | (y12 & y13);
assign y15 = a1 & b3;
//full adder-
assign y16 = (y15 ^ y14) ^ c4;
assign c7 = ((y15 ^ y14) & c4) | (y15 & y14);
//half adder - 
assign p4 = y16 ^ c5;
assign c8 = y16 & c5;

assign y17 = a2 & b3;
assign y18 = a3 & b2;
//full adder-
assign y19 = (y17 ^ y18) ^ c6;
assign c9 = ((y17 ^ y18) & c6) | (y17 & y18);
//full adder-
assign p5 = (y19 ^ c7) ^ c8;
assign c10 = ((y19 ^ c7) & c8) | (y19 & c7);

assign y20 = a3 & b3;
//full adder-
assign p6 = (y20 ^ c9) ^ c10;
assign p7 = ((y20 ^ c9) & c10) | (y20 & c9);

endmodule

VLSI/project/verilog/multiplier_tb.v
`timescale 1ns/10ps

module multiplier_tb;

reg a0,a1,a2,a3,b0,b1,b2,b3;
wire p0,p1,p2,p3,p4,p5,p6,p7;
integer i;

multiplier UUT (a0,a1,a2,a3,b0,b1,b2,b3,p0,p1,p2,p3,p4,p5,p6,p7);

initial
    begin
        $dumpfile("multiplier_tb.vcd");
        $dumpvars(0,multiplier_tb);

        a0 = 0;
        a1 = 0;
        a2 = 0;
        a3 = 0;
        b0 = 0;
        b1 = 0;
        b2 = 0;
        b3 = 0;
    end

initial
    begin
        
       begin
        
        for(i=0;i<256;i=i+1)
        begin
            {a3,a2,a1,a0,b3,b2,b1,b0} = i;
            #10;
        end

    end

    end

always @(b0)
$display("time =%0t \t a3=%b, a2=%b, a1=%b, a0=%b  ;  b3=%b, b2=%b, b1=%b, b0=%b  ;  p7=%b, p6=%b, p5=%b, p4=%b, p3=%b, p2=%b, p1=%b, p0=%b",$time,a3,a2,a1,a0,b3,b2,b1,b0,p7,p6,p5,p4,p3,p2,p1,p0);

endmodule

VLSI/project/verilog/multiplier_tb.vcd
$date
	Wed Nov 30 00:51:26 2022
$end
$version
	Icarus Verilog
$end
$timescale
	10ps
$end
$scope module multiplier_tb $end
$var wire 1 ! p7 $end
$var wire 1 " p6 $end
$var wire 1 # p5 $end
$var wire 1 $ p4 $end
$var wire 1 % p3 $end
$var wire 1 & p2 $end
$var wire 1 ' p1 $end
$var wire 1 ( p0 $end
$var reg 1 ) a0 $end
$var reg 1 * a1 $end
$var reg 1 + a2 $end
$var reg 1 , a3 $end
$var reg 1 - b0 $end
$var reg 1 . b1 $end
$var reg 1 / b2 $end
$var reg 1 0 b3 $end
$var integer 32 1 i [31:0] $end
$scope module UUT $end
$var wire 1 ) a0 $end
$var wire 1 * a1 $end
$var wire 1 + a2 $end
$var wire 1 , a3 $end
$var wire 1 - b0 $end
$var wire 1 . b1 $end
$var wire 1 / b2 $end
$var wire 1 0 b3 $end
$var wire 1 2 c0 $end
$var wire 1 3 c1 $end
$var wire 1 4 c10 $end
$var wire 1 5 c2 $end
$var wire 1 6 c3 $end
$var wire 1 7 c4 $end
$var wire 1 8 c5 $end
$var wire 1 9 c6 $end
$var wire 1 : c7 $end
$var wire 1 ; c8 $end
$var wire 1 < c9 $end
$var wire 1 ( p0 $end
$var wire 1 ' p1 $end
$var wire 1 & p2 $end
$var wire 1 % p3 $end
$var wire 1 $ p4 $end
$var wire 1 # p5 $end
$var wire 1 " p6 $end
$var wire 1 ! p7 $end
$var wire 1 = y0 $end
$var wire 1 > y1 $end
$var wire 1 ? y10 $end
$var wire 1 @ y11 $end
$var wire 1 A y12 $end
$var wire 1 B y13 $end
$var wire 1 C y14 $end
$var wire 1 D y15 $end
$var wire 1 E y16 $end
$var wire 1 F y17 $end
$var wire 1 G y18 $end
$var wire 1 H y19 $end
$var wire 1 I y2 $end
$var wire 1 J y20 $end
$var wire 1 K y3 $end
$var wire 1 L y4 $end
$var wire 1 M y5 $end
$var wire 1 N y6 $end
$var wire 1 O y7 $end
$var wire 1 P y8 $end
$var wire 1 Q y9 $end
$upscope $end
$upscope $end
$enddefinitions $end
#0
$dumpvars
0Q
0P
0O
0N
0M
0L
0K
0J
0I
0H
0G
0F
0E
0D
0C
0B
0A
0@
0?
0>
0=
0<
0;
0:
09
08
07
06
05
04
03
02
b0 1
00
0/
0.
0-
0,
0+
0*
0)
0(
0'
0&
0%
0$
0#
0"
0!
$end
#1000
1-
b1 1
#2000
1.
0-
b10 1
#3000
1-
b11 1
#4000
1/
0.
0-
b100 1
#5000
1-
b101 1
#6000
1.
0-
b110 1
#7000
1-
b111 1
#8000
10
0/
0.
0-
b1000 1
#9000
1-
b1001 1
#10000
1.
0-
b1010 1
#11000
1-
b1011 1
#12000
1/
0.
0-
b1100 1
#13000
1-
b1101 1
#14000
1.
0-
b1110 1
#15000
1-
b1111 1
#16000
1)
00
0/
0.
0-
b10000 1
#17000
1(
1-
b10001 1
#18000
1'
1=
0(
1.
0-
b10010 1
#19000
1(
1-
b10011 1
#20000
1&
0'
1L
0=
0(
1/
0.
0-
b10100 1
#21000
1(
1-
b10101 1
#22000
1'
1=
0(
1.
0-
b10110 1
#23000
1(
1-
b10111 1
#24000
1%
0&
0'
1@
0L
0=
0(
10
0/
0.
0-
b11000 1
#25000
1(
1-
b11001 1
#26000
1'
1=
0(
1.
0-
b11010 1
#27000
1(
1-
b11011 1
#28000
1&
0'
1L
0=
0(
1/
0.
0-
b11100 1
#29000
1(
1-
b11101 1
#30000
1'
1=
0(
1.
0-
b11110 1
#31000
1(
1-
b11111 1
#32000
0%
0&
0'
0@
0L
0=
0(
1*
0)
00
0/
0.
0-
b100000 1
#33000
1'
1>
1-
b100001 1
#34000
1&
1M
0'
1I
0>
1.
0-
b100010 1
#35000
1'
1>
1-
b100011 1
#36000
1%
0&
1?
0M
0'
1Q
0I
0>
1/
0.
0-
b100100 1
#37000
1'
1>
1-
b100101 1
#38000
1&
1M
0'
1I
0>
1.
0-
b100110 1
#39000
1'
1>
1-
b100111 1
#40000
0%
1$
0&
1E
0?
0M
0'
1D
0Q
0I
0>
10
0/
0.
0-
b101000 1
#41000
1'
1>
1-
b101001 1
#42000
1&
1M
0'
1I
0>
1.
0-
b101010 1
#43000
1'
1>
1-
b101011 1
#44000
1%
0&
1?
0M
0'
1Q
0I
0>
1/
0.
0-
b101100 1
#45000
1'
1>
1-
b101101 1
#46000
1&
1M
0'
1I
0>
1.
0-
b101110 1
#47000
1'
1>
1-
b101111 1
#48000
0%
0$
0&
0E
0?
0M
0'
0D
0Q
0I
0>
1)
00
0/
0.
0-
b110000 1
#49000
1'
1(
1>
1-
b110001 1
#50000
1&
1M
1=
1I
0(
0>
1.
0-
b110010 1
#51000
1%
15
0&
0'
12
1(
1>
1-
b110011 1
#52000
05
1?
1&
0M
02
1L
1Q
0=
0I
0(
0>
1/
0.
0-
b110100 1
#53000
1'
1(
1>
1-
b110101 1
#54000
1$
18
0%
0&
15
1M
1=
1I
0(
0>
1.
0-
b110110 1
#55000
1&
0'
12
1(
1>
1-
b110111 1
#56000
0#
1%
08
1$
0;
1E
05
0?
0&
0M
02
1@
1D
0L
0Q
0=
0I
0(
0>
10
0/
0.
0-
b111000 1
#57000
1'
1(
1>
1-
b111001 1
#58000
1&
1M
1=
1I
0(
0>
1.
0-
b111010 1
#59000
1#
0$
1;
18
0%
15
0&
0'
12
1(
1>
1-
b111011 1
#60000
05
1?
1&
0M
02
1L
1Q
0=
0I
0(
0>
1/
0.
0-
b111100 1
#61000
1'
1(
1>
1-
b111101 1
#62000
1%
0&
15
1M
1=
1I
0(
0>
1.
0-
b111110 1
#63000
1&
0'
12
1(
1>
1-
b111111 1
#64000
0#
0%
0;
08
0E
05
0?
0&
0M
02
0@
0D
0L
0Q
0=
0I
0(
0>
1+
0*
0)
00
0/
0.
0-
b1000000 1
#65000
1&
1M
1K
1-
b1000001 1
#66000
1%
1?
0&
1P
0M
1N
0K
1.
0-
b1000010 1
#67000
1&
1M
1K
1-
b1000011 1
#68000
1$
0%
1E
0?
0&
1C
0P
0M
1B
0N
0K
1/
0.
0-
b1000100 1
#69000
1&
1M
1K
1-
b1000101 1
#70000
1%
1?
0&
1P
0M
1N
0K
1.
0-
b1000110 1
#71000
1&
1M
1K
1-
b1000111 1
#72000
0$
0%
1#
0E
0?
0&
1H
0C
0P
0M
1F
0B
0N
0K
10
0/
0.
0-
b1001000 1
#73000
1&
1M
1K
1-
b1001001 1
#74000
1%
1?
0&
1P
0M
1N
0K
1.
0-
b1001010 1
#75000
1&
1M
1K
1-
b1001011 1
#76000
1$
0%
1E
0?
0&
1C
0P
0M
1B
0N
0K
1/
0.
0-
b1001100 1
#77000
1&
1M
1K
1-
b1001101 1
#78000
1%
1?
0&
1P
0M
1N
0K
1.
0-
b1001110 1
#79000
1&
1M
1K
1-
b1001111 1
#80000
0$
0%
0#
0E
0?
0&
0H
0C
0P
0M
0F
0B
0N
0K
1)
00
0/
0.
0-
b1010000 1
#81000
1&
1M
1(
1K
1-
b1010001 1
#82000
1%
1?
0&
1'
1P
0M
1=
1N
0(
0K
1.
0-
b1010010 1
#83000
1&
1M
1(
1K
1-
b1010011 1
#84000
1$
0%
1E
0?
1C
0'
0P
0M
1L
1B
0=
0N
0(
0K
1/
0.
0-
b1010100 1
#85000
1%
0&
15
1M
1(
1K
1-
b1010101 1
#86000
1%
1?
1&
05
1'
1P
0M
1=
1N
0(
0K
1.
0-
b1010110 1
#87000
1#
0$
1;
18
0%
0&
15
1M
1(
1K
1-
b1010111 1
#88000
0"
04
0;
1%
08
1#
0E
0?
1H
05
0C
0'
0P
0M
1@
1F
0L
0B
0=
0N
0(
0K
10
0/
0.
0-
b1011000 1
#89000
1&
1M
1(
1K
1-
b1011001 1
#90000
1$
0%
18
1?
0&
1'
1P
0M
1=
1N
0(
0K
1.
0-
b1011010 1
#91000
1&
1M
1(
1K
1-
b1011011 1
#92000
1%
08
1E
0?
1C
0'
0P
0M
1L
1B
0=
0N
0(
0K
1/
0.
0-
b1011100 1
#93000
1"
14
0#
0$
1;
18
0%
0&
15
1M
1(
1K
1-
b1011101 1
#94000
0%
1?
1&
05
1'
1P
0M
1=
1N
0(
0K
1.
0-
b1011110 1
#95000
1%
0&
15
1M
1(
1K
1-
b1011111 1
#96000
0"
04
0%
0E
0$
0;
0?
08
0H
05
0C
0'
0P
0M
0@
0F
0L
0B
0=
0N
0(
0K
1*
0)
00
0/
0.
0-
b1100000 1
#97000
1&
1'
1M
1>
1K
1-
b1100001 1
#98000
1%
1?
1P
0'
1I
1N
0>
0K
1.
0-
b1100010 1
#99000
1$
0%
1E
0&
17
0?
1'
0M
13
1>
1K
1-
b1100011 1
#100000
1%
07
1C
1?
0P
0'
03
1Q
1B
0I
0N
0>
0K
1/
0.
0-
b1100100 1
#101000
1&
1'
1M
1>
1K
1-
b1100101 1
#102000
1#
0%
0$
1:
0E
0?
17
1P
0'
1I
1N
0>
0K
1.
0-
b1100110 1
#103000
1%
0&
1?
1'
0M
13
1>
1K
1-
b1100111 1
#104000
0"
1$
1#
04
1E
0%
0:
1H
07
0C
0?
0P
0'
03
1D
1F
0Q
0B
0I
0N
0>
0K
10
0/
0.
0-
b1101000 1
#105000
1&
1'
1M
1>
1K
1-
b1101001 1
#106000
1%
1?
1P
0'
1I
1N
0>
0K
1.
0-
b1101010 1
#107000
1"
0#
14
0$
1:
0%
0E
0&
17
0?
1'
0M
13
1>
1K
1-
b1101011 1
#108000
1%
07
1C
1?
0P
0'
03
1Q
1B
0I
0N
0>
0K
1/
0.
0-
b1101100 1
#109000
1&
1'
1M
1>
1K
1-
b1101101 1
#110000
0%
1$
1E
0?
17
1P
0'
1I
1N
0>
0K
1.
0-
b1101110 1
#111000
1%
0&
1?
1'
0M
13
1>
1K
1-
b1101111 1
#112000
0"
0$
04
0E
0%
0:
0H
07
0C
0?
0P
0'
03
0D
0F
0Q
0B
0I
0N
0>
0K
1)
00
0/
0.
0-
b1110000 1
#113000
1&
1'
1M
1(
1>
1K
1-
b1110001 1
#114000
1%
1?
1P
1=
1I
1N
0(
0>
0K
1.
0-
b1110010 1
#115000
1$
0%
1E
17
0?
0'
12
0M
13
1(
1>
1K
1-
b1110011 1
#116000
1%
07
1C
1?
0P
02
03
1L
1Q
1B
0=
0I
0N
0(
0>
0K
1/
0.
0-
b1110100 1
#117000
1#
0$
1;
18
0%
0&
15
1'
1M
1(
1>
1K
1-
b1110101 1
#118000
08
1%
0$
0;
1:
0E
0?
17
1P
1=
1I
1N
0(
0>
0K
1.
0-
b1110110 1
#119000
1$
18
0%
1?
0'
12
0M
13
1(
1>
1K
1-
b1110111 1
#120000
0"
1#
04
1E
08
0:
05
1%
1H
07
0C
0?
0P
02
03
1@
1D
1F
0L
0Q
0B
0=
0I
0N
0(
0>
0K
10
0/
0.
0-
b1111000 1
#121000
1&
1'
1M
1(
1>
1K
1-
b1111001 1
#122000
1"
14
0#
0$
1;
0%
18
1?
1P
1=
1I
1N
0(
0>
0K
1.
0-
b1111010 1
#123000
0;
1:
1%
08
0E
17
0?
0'
12
0M
13
1(
1>
1K
1-
b1111011 1
#124000
1$
0%
18
07
1C
1?
0P
02
03
1L
1Q
1B
0=
0I
0N
0(
0>
0K
1/
0.
0-
b1111100 1
#125000
1%
0&
15
1'
1M
1(
1>
1K
1-
b1111101 1
#126000
1#
0%
18
0$
1;
1E
0?
17
1P
1=
1I
1N
0(
0>
0K
1.
0-
b1111110 1
#127000
1%
1?
0'
12
0M
13
1(
1>
1K
1-
b1111111 1
#128000
0"
0#
04
0E
0$
0;
05
0%
08
0:
0H
07
0C
0?
0P
02
03
0@
0D
0F
0L
0Q
0B
0=
0I
0N
0(
0>
0K
1,
0+
0*
0)
00
0/
0.
0-
b10000000 1
#129000
1%
1?
1P
1O
1-
b10000001 1
#130000
1$
0%
1E
0?
1C
0P
1A
0O
1.
0-
b10000010 1
#131000
1%
1?
1P
1O
1-
b10000011 1
#132000
0$
0%
1#
0E
0?
1H
0C
0P
1G
0A
0O
1/
0.
0-
b10000100 1
#133000
1%
1?
1P
1O
1-
b10000101 1
#134000
1$
0%
1E
0?
1C
0P
1A
0O
1.
0-
b10000110 1
#135000
1%
1?
1P
1O
1-
b10000111 1
#136000
0$
0%
0#
0E
0?
1"
0H
0C
0P
1J
0G
0A
0O
10
0/
0.
0-
b10001000 1
#137000
1%
1?
1P
1O
1-
b10001001 1
#138000
1$
0%
1E
0?
1C
0P
1A
0O
1.
0-
b10001010 1
#139000
1%
1?
1P
1O
1-
b10001011 1
#140000
0$
0%
1#
0E
0?
1H
0C
0P
1G
0A
0O
1/
0.
0-
b10001100 1
#141000
1%
1?
1P
1O
1-
b10001101 1
#142000
1$
0%
1E
0?
1C
0P
1A
0O
1.
0-
b10001110 1
#143000
1%
1?
1P
1O
1-
b10001111 1
#144000
0$
0%
0#
0E
0?
0"
0H
0C
0P
0J
0G
0A
0O
1)
00
0/
0.
0-
b10010000 1
#145000
1%
1?
1P
1(
1O
1-
b10010001 1
#146000
1$
0%
1E
0?
1C
1'
0P
1=
1A
0(
0O
1.
0-
b10010010 1
#147000
1%
1?
1P
1(
1O
1-
b10010011 1
#148000
0$
0%
1#
0E
0?
1&
1H
0C
0'
0P
1L
1G
0=
0A
0(
0O
1/
0.
0-
b10010100 1
#149000
1%
1?
1P
1(
1O
1-
b10010101 1
#150000
1$
0%
1E
0?
1C
1'
0P
1=
1A
0(
0O
1.
0-
b10010110 1
#151000
1%
1?
1P
1(
1O
1-
b10010111 1
#152000
0#
0E
0$
0;
0?
1%
08
1"
0&
0H
0C
0'
0P
1@
1J
0L
0G
0=
0A
0(
0O
10
0/
0.
0-
b10011000 1
#153000
1$
0%
18
1?
1P
1(
1O
1-
b10011001 1
#154000
1%
08
1E
0?
1C
1'
0P
1=
1A
0(
0O
1.
0-
b10011010 1
#155000
1#
0$
1;
0%
18
1?
1P
1(
1O
1-
b10011011 1
#156000
0!
1"
04
0;
1%
08
1#
0E
0?
1&
1H
0C
0'
0P
1L
1G
0=
0A
0(
0O
1/
0.
0-
b10011100 1
#157000
1$
0%
18
1?
1P
1(
1O
1-
b10011101 1
#158000
1%
08
1E
0?
1C
1'
0P
1=
1A
0(
0O
1.
0-
b10011110 1
#159000
1!
0"
14
0#
0$
1;
0%
18
1?
1P
1(
1O
1-
b10011111 1
#160000
04
0E
0$
0;
0!
0?
0%
08
0"
0&
0H
0C
0'
0P
0@
0J
0L
0G
0=
0A
0(
0O
1*
0)
00
0/
0.
0-
b10100000 1
#161000
1%
1?
1'
1P
1>
1O
1-
b10100001 1
#162000
1$
0%
1E
1&
0?
1C
1M
0'
0P
1I
1A
0>
0O
1.
0-
b10100010 1
#163000
1%
1?
1'
1P
1>
1O
1-
b10100011 1
#164000
0$
1#
0E
0&
1H
0C
0M
0'
0P
1Q
1G
0I
0A
0>
0O
1/
0.
0-
b10100100 1
#165000
0%
1$
1E
0?
17
1'
1P
1>
1O
1-
b10100101 1
#166000
1%
1&
1?
07
1C
1M
0'
0P
1I
1A
0>
0O
1.
0-
b10100110 1
#167000
1"
0#
14
0%
0$
1:
0E
0?
17
1'
1P
1>
1O
1-
b10100111 1
#168000
1$
0#
04
1E
0:
0!
0&
1"
07
0H
0C
0M
0'
0P
1D
1J
0Q
0G
0I
0A
0>
0O
10
0/
0.
0-
b10101000 1
#169000
1%
1?
1'
1P
1>
1O
1-
b10101001 1
#170000
1#
0$
0%
0E
1:
1&
0?
1C
1M
0'
0P
1I
1A
0>
0O
1.
0-
b10101010 1
#171000
1%
1?
1'
1P
1>
1O
1-
b10101011 1
#172000
0!
1"
1$
1#
04
1E
0:
0&
1H
0C
0M
0'
0P
1Q
1G
0I
0A
0>
0O
1/
0.
0-
b10101100 1
#173000
1!
0"
0#
14
0%
0$
1:
0E
0?
17
1'
1P
1>
1O
1-
b10101101 1
#174000
1%
1&
1?
07
1C
1M
0'
0P
1I
1A
0>
0O
1.
0-
b10101110 1
#175000
0%
1$
1E
0?
17
1'
1P
1>
1O
1-
b10101111 1
#176000
0$
04
0E
0!
0&
0:
0"
07
0H
0C
0M
0'
0P
0D
0J
0Q
0G
0I
0A
0>
0O
1)
00
0/
0.
0-
b10110000 1
#177000
1%
1?
1'
1P
1(
1>
1O
1-
b10110001 1
#178000
1$
0%
1E
1&
0?
1C
1M
0P
1=
1I
1A
0(
0>
0O
1.
0-
b10110010 1
#179000
1#
0$
1;
18
15
1?
0&
0'
12
1P
1(
1>
1O
1-
b10110011 1
#180000
0"
04
0;
08
1#
0E
1%
05
1H
0C
1&
0M
02
0P
1L
1Q
1G
0=
0I
0A
0(
0>
0O
1/
0.
0-
b10110100 1
#181000
0%
1$
1E
0?
17
1'
1P
1(
1>
1O
1-
b10110101 1
#182000
1"
14
0#
0$
1;
18
0&
15
1?
07
1C
1M
0P
1=
1I
1A
0(
0>
0O
1.
0-
b10110110 1
#183000
08
1%
0$
0;
1:
0E
0?
17
1&
0'
12
1P
1(
1>
1O
1-
b10110111 1
#184000
1$
0#
04
1E
0:
0!
1"
05
07
0H
0C
0&
0M
02
0P
1@
1D
1J
0L
0Q
0G
0=
0I
0A
0(
0>
0O
10
0/
0.
0-
b10111000 1
#185000
1#
0$
1;
0%
18
1?
1'
1P
1(
1>
1O
1-
b10111001 1
#186000
0;
1%
08
0E
1:
1&
0?
1C
1M
0P
1=
1I
1A
0(
0>
0O
1.
0-
b10111010 1
#187000
1$
18
15
1?
0&
0'
12
1P
1(
1>
1O
1-
b10111011 1
#188000
1!
0"
0$
1;
0#
14
1E
0:
0%
05
1H
0C
1&
0M
02
0P
1L
1Q
1G
0=
0I
0A
0(
0>
0O
1/
0.
0-
b10111100 1
#189000
1%
08
0$
0;
1:
0E
0?
17
1'
1P
1(
1>
1O
1-
b10111101 1
#190000
1$
18
0&
15
1?
07
1C
1M
0P
1=
1I
1A
0(
0>
0O
1.
0-
b10111110 1
#191000
1#
0%
18
0$
1;
1E
0?
17
1&
0'
12
1P
1(
1>
1O
1-
b10111111 1
#192000
0#
0;
04
0E
08
0!
0:
0"
05
07
0H
0C
0&
0M
02
0P
0@
0D
0J
0L
0Q
0G
0=
0I
0A
0(
0>
0O
1+
0*
0)
00
0/
0.
0-
b11000000 1
#193000
1%
1&
1?
1M
1P
1K
1O
1-
b11000001 1
#194000
1$
1E
0&
1C
0M
1N
1A
0K
0O
1.
0-
b11000010 1
#195000
1#
0%
0$
0E
1H
1&
0?
19
0C
1M
0P
16
1K
1O
1-
b11000011 1
#196000
0"
1$
1#
1E
0<
0&
09
1H
1C
0M
06
1B
1G
0N
0A
0K
0O
1/
0.
0-
b11000100 1
#197000
1%
1&
1?
1M
1P
1K
1O
1-
b11000101 1
#198000
1"
0$
0#
0E
1<
0H
0&
0C
19
0M
1N
1A
0K
0O
1.
0-
b11000110 1
#199000
0%
1$
1E
1&
0?
1C
1M
0P
16
1K
1O
1-
b11000111 1
#200000
1#
0$
0<
0E
1H
0&
1"
0!
09
0C
0M
06
1F
1J
0B
0G
0N
0A
0K
0O
10
0/
0.
0-
b11001000 1
#201000
1%
1&
1?
1M
1P
1K
1O
1-
b11001001 1
#202000
1$
1E
0&
1C
0M
1N
1A
0K
0O
1.
0-
b11001010 1
#203000
0"
1!
0#
0%
0$
1<
0E
0H
1&
0?
19
0C
1M
0P
16
1K
1O
1-
b11001011 1
#204000
1$
0#
1E
0&
09
0H
1C
0M
06
1B
1G
0N
0A
0K
0O
1/
0.
0-
b11001100 1
#205000
1%
1&
1?
1M
1P
1K
1O
1-
b11001101 1
#206000
0$
1#
0E
1H
0&
0C
19
0M
1N
1A
0K
0O
1.
0-
b11001110 1
#207000
0%
1$
1E
1&
0?
1C
1M
0P
16
1K
1O
1-
b11001111 1
#208000
0#
0$
0E
0H
0&
0"
0!
0<
09
0C
0M
06
0F
0J
0B
0G
0N
0A
0K
0O
1)
00
0/
0.
0-
b11010000 1
#209000
1%
1&
1?
1M
1P
1(
1K
1O
1-
b11010001 1
#210000
1$
1E
0&
1C
1'
0M
1=
1N
1A
0(
0K
0O
1.
0-
b11010010 1
#211000
1#
0%
0$
0E
1H
1&
0?
19
0C
1M
0P
16
1(
1K
1O
1-
b11010011 1
#212000
0"
1$
1#
1E
0<
09
1H
1C
0'
0M
06
1L
1B
1G
0=
0N
0A
0(
0K
0O
1/
0.
0-
b11010100 1
#213000
1"
14
0#
0$
1;
18
0&
15
1?
1M
1P
1(
1K
1O
1-
b11010101 1
#214000
0!
04
1"
0;
0#
08
0E
1<
1%
0H
1&
05
0C
19
1'
0M
1=
1N
1A
0(
0K
0O
1.
0-
b11010110 1
#215000
1$
1E
0&
15
0?
1C
1M
0P
16
1(
1K
1O
1-
b11010111 1
#216000
1#
0$
0<
0E
1H
1"
0!
05
09
0C
0'
0M
06
1@
1F
1J
0L
0B
0G
0=
0N
0A
0(
0K
0O
10
0/
0.
0-
b11011000 1
#217000
1$
0%
18
1&
1?
1M
1P
1(
1K
1O
1-
b11011001 1
#218000
1!
0"
14
0#
0$
1;
1E
0&
1C
1'
0M
1=
1N
1A
0(
0K
0O
1.
0-
b11011010 1
#219000
04
0"
1%
08
0$
0;
1<
0E
0H
1&
0?
19
0C
1M
0P
16
1(
1K
1O
1-
b11011011 1
#220000
1$
0#
1E
09
0H
1C
0'
0M
06
1L
1B
1G
0=
0N
0A
0(
0K
0O
1/
0.
0-
b11011100 1
#221000
1#
0$
1;
18
0&
15
1?
1M
1P
1(
1K
1O
1-
b11011101 1
#222000
0"
04
1$
0;
1#
0E
0%
1H
1&
05
0C
19
1'
0M
1=
1N
1A
0(
0K
0O
1.
0-
b11011110 1
#223000
1"
14
0#
0$
1;
1E
0&
15
0?
1C
1M
0P
16
1(
1K
1O
1-
b11011111 1
#224000
04
0;
0E
08
0H
0"
0!
05
0<
09
0C
0'
0M
06
0@
0F
0J
0L
0B
0G
0=
0N
0A
0(
0K
0O
1*
0)
00
0/
0.
0-
b11100000 1
#225000
1%
1&
1?
1'
1M
1P
1>
1K
1O
1-
b11100001 1
#226000
1$
1E
1C
0'
1I
1N
1A
0>
0K
0O
1.
0-
b11100010 1
#227000
1#
0$
0E
1H
0&
19
0C
1'
0M
13
0P
16
1>
1K
1O
1-
b11100011 1
#228000
0"
1$
1#
1E
0<
09
1H
1C
0'
03
06
1Q
1B
1G
0I
0N
0A
0>
0K
0O
1/
0.
0-
b11100100 1
#229000
1"
0#
14
0%
0$
1:
0E
1&
0?
17
1'
1M
1P
1>
1K
1O
1-
b11100101 1
#230000
1$
0:
0#
04
1E
1<
0H
0C
19
0'
1I
1N
1A
0>
0K
0O
1.
0-
b11100110 1
#231000
1#
0$
1:
0E
0&
1C
1'
0M
13
0P
16
1>
1K
1O
1-
b11100111 1
#232000
0<
1$
0:
1H
07
1E
1"
0!
09
0C
0'
03
06
1D
1F
1J
0Q
0B
0G
0I
0N
0A
0>
0K
0O
10
0/
0.
0-
b11101000 1
#233000
1%
1&
1?
1'
1M
1P
1>
1K
1O
1-
b11101001 1
#234000
1!
0"
0#
14
0$
0E
1:
1C
0'
1I
1N
1A
0>
0K
0O
1.
0-
b11101010 1
#235000
04
1$
1<
1E
0:
0H
0&
19
0C
1'
0M
13
0P
16
1>
1K
1O
1-
b11101011 1
#236000
0$
1#
0E
1:
09
0H
1C
0'
03
06
1Q
1B
1G
0I
0N
0A
0>
0K
0O
1/
0.
0-
b11101100 1
#237000
0%
1$
1E
1&
0?
17
1'
1M
1P
1>
1K
1O
1-
b11101101 1
#238000
1"
0$
0#
14
0E
1:
1H
0C
19
0'
1I
1N
1A
0>
0K
0O
1.
0-
b11101110 1
#239000
1$
1E
0&
1C
1'
0M
13
0P
16
1>
1K
1O
1-
b11101111 1
#240000
0#
04
0$
0H
07
0E
0:
0"
0!
0<
09
0C
0'
03
06
0D
0F
0J
0Q
0B
0G
0I
0N
0A
0>
0K
0O
1)
00
0/
0.
0-
b11110000 1
#241000
1%
1&
1?
1'
1M
1P
1(
1>
1K
1O
1-
b11110001 1
#242000
1$
1E
1C
1=
1I
1N
1A
0(
0>
0K
0O
1.
0-
b11110010 1
#243000
1#
0$
0E
1H
19
0C
0'
12
0M
13
0P
16
1(
1>
1K
1O
1-
b11110011 1
#244000
0"
1$
1#
1E
0<
09
1H
1C
02
03
06
1L
1Q
1B
1G
0=
0I
0N
0A
0(
0>
0K
0O
1/
0.
0-
b11110100 1
#245000
1"
0#
14
0$
1:
0E
0&
15
0?
17
1'
1M
1P
1(
1>
1K
1O
1-
b11110101 1
#246000
1$
0:
0#
04
1E
1<
0H
0C
19
1=
1I
1N
1A
0(
0>
0K
0O
1.
0-
b11110110 1
#247000
1#
0$
1:
0E
1C
0'
12
0M
13
0P
16
1(
1>
1K
1O
1-
b11110111 1
#248000
04
1#
0;
0<
08
1$
0:
1H
05
07
1%
1E
1"
0!
09
0C
02
03
06
1@
1D
1F
1J
0L
0Q
0B
0G
0=
0I
0N
0A
0(
0>
0K
0O
10
0/
0.
0-
b11111000 1
#249000
1!
0"
14
0#
0$
1;
0%
18
1&
1?
1'
1M
1P
1(
1>
1K
1O
1-
b11111001 1
#250000
1$
0;
0E
1:
1C
1=
1I
1N
1A
0(
0>
0K
0O
1.
0-
b11111010 1
#251000
1#
04
0$
1;
1<
1E
0:
0H
19
0C
0'
12
0M
13
0P
16
1(
1>
1K
1O
1-
b11111011 1
#252000
0"
04
1$
0;
1#
0E
1:
09
0H
1C
02
03
06
1L
1Q
1B
1G
0=
0I
0N
0A
0(
0>
0K
0O
1/
0.
0-
b11111100 1
#253000
1"
14
0#
0$
1;
1E
0&
15
0?
17
1'
1M
1P
1(
1>
1K
1O
1-
b11111101 1
#254000
1"
14
1$
0;
0#
0E
1:
1H
0C
19
1=
1I
1N
1A
0(
0>
0K
0O
1.
0-
b11111110 1
#255000
1#
0$
1;
1E
1C
0'
12
0M
13
0P
16
1(
1>
1K
1O
1-
b11111111 1
#256000
b100000000 1
